Metadata-Version: 2.1
Name: www-robot
Version: 1.0.2
Summary: A WWW Robot library for Python
Home-page: https://github.com/Camroku/www-robot
Author: Cinar Yilmaz
Author-email: cinaryilmaz.gnu@gmail.com
License: MIT
Keywords: www,robot,python,scraping
Platform: UNKNOWN
Classifier: Operating System :: OS Independent
License-File: LICENSE
